eda_visualizer/__init__.py
eda_visualizer/eda.py
eda_visualizer-1.0.3.1.dist-info/LICENSE
eda_visualizer-1.0.3.1.dist-info/METADATA
eda_visualizer-1.0.3.1.dist-info/WHEEL
eda_visualizer-1.0.3.1.dist-info/top_level.txt
eda_visualizer-1.0.3.1.dist-info/RECORD
